populate_dotenv/__init__.py
populate_dotenv/__main__.py
populate_dotenv/main.py
populate_dotenv-0.1.1.dist-info/LICENSE
populate_dotenv-0.1.1.dist-info/METADATA
populate_dotenv-0.1.1.dist-info/WHEEL
populate_dotenv-0.1.1.dist-info/RECORD
