Metadata-Version: 2.1
Name: populate_dotenv
Version: 0.1.1
Summary: 
Author: Luca Mattiazzi
Author-email: luca.mattiazzi@illimity.com
Requires-Python: >=3.11,<4.0
Classifier: Programming Language :: Python :: 3
Classifier: Programming Language :: Python :: 3.11
Classifier: Programming Language :: Python :: 3.12
Requires-Dist: azure-identity (>=1.16.0,<2.0.0)
Requires-Dist: azure-keyvault-secrets (>=4.8.0,<5.0.0)
Requires-Dist: click (>=8.1.7,<9.0.0)
Requires-Dist: python-dotenv (>=1.0.1,<2.0.0)
